virtualenv_tools.py
virtualenv_tools_enhanced-1.0.0.dist-info/LICENSE
virtualenv_tools_enhanced-1.0.0.dist-info/METADATA
virtualenv_tools_enhanced-1.0.0.dist-info/WHEEL
virtualenv_tools_enhanced-1.0.0.dist-info/entry_points.txt
virtualenv_tools_enhanced-1.0.0.dist-info/top_level.txt
virtualenv_tools_enhanced-1.0.0.dist-info/RECORD
