Metadata-Version: 2.1
Name: virtualenv-tools-enhanced
Version: 1.0.0
Summary: A set of tools to relocate virtualenv (and main installation on Windows)
Home-page: https://github.com/psolyca/virtualenv-tools
Author: Fireteam Ltd.; Yelp, Inc.; Damien "psolyca" Gaignon
Author-email: damien.gaignon@gmail.com
License: UNKNOWN
Platform: UNKNOWN
Classifier: License :: OSI Approved :: BSD License
Classifier: Programming Language :: Python :: 3
Classifier: Programming Language :: Python :: 3.6
Classifier: Programming Language :: Python :: 3.7
Classifier: Programming Language :: Python :: 3.8
Classifier: Programming Language :: Python :: 3.9
